git_fixer/__init__.py
git_fixer/src/__init__.py
git_fixer/src/fake_git_history.py
git_fixer-0.1.3.dist-info/METADATA
git_fixer-0.1.3.dist-info/WHEEL
git_fixer-0.1.3.dist-info/entry_points.txt
git_fixer-0.1.3.dist-info/top_level.txt
git_fixer-0.1.3.dist-info/RECORD
