Metadata-Version: 2.4
Name: git-fixer
Version: 0.1.3
Summary: Generate fake git commits to create realistic GitHub activity graphs
Home-page: https://github.com/SirNosh/git-fixer
Author: Dev Vyas
Author-email: devvyas17272@gmail.com
License: MIT
Keywords: git,github,contribution,activity,commit,history
Classifier: Development Status :: 3 - Alpha
Classifier: Intended Audience :: Developers
Classifier: Programming Language :: Python :: 3
Classifier: Programming Language :: Python :: 3.6
Classifier: Programming Language :: Python :: 3.7
Classifier: Programming Language :: Python :: 3.8
Classifier: Programming Language :: Python :: 3.9
Classifier: Programming Language :: Python :: 3.10
Classifier: Programming Language :: Python :: 3.11
Classifier: Topic :: Software Development :: Version Control :: Git
Requires-Python: >=3.6
Dynamic: author
Dynamic: author-email
Dynamic: classifier
Dynamic: description
Dynamic: description-content-type
Dynamic: home-page
Dynamic: keywords
Dynamic: license
Dynamic: requires-python
Dynamic: summary
